core_service/__init__.py
core_service/abstract.py
core_service/base.py
core_service/container.py
core_service/decorators.py
core_service/exceptions.py
core_service/logging.py
core_service/tasks.py
tests/__init__.py
tests/test_decorators.py
tests/test_nested_services.py
tests/test_service.py
tests/test_service_tasks.py
tests/test_task_collection.py
core_service-0.1.2.dist-info/METADATA
core_service-0.1.2.dist-info/WHEEL
core_service-0.1.2.dist-info/top_level.txt
core_service-0.1.2.dist-info/RECORD
