Metadata-Version: 2.1
Name: core-service
Version: 0.1.2
Summary: asyncio service microframework
Home-page: https://github.com/sarafanio/core-service.git
Author: Sarafan Community
Author-email: flu2020@pm.me
License: UNKNOWN
Platform: UNKNOWN
Provides-Extra: dev
Requires-Dist: pytest ; extra == 'dev'
Requires-Dist: pytest-asyncio ; extra == 'dev'
Requires-Dist: pytest-cov ; extra == 'dev'
Requires-Dist: pylama ; extra == 'dev'
Requires-Dist: mypy ; extra == 'dev'
Requires-Dist: Sphinx ; extra == 'dev'
